.gitignore
CHANGES.rst
MANIFEST.in
README.txt
communesplone.layout-configure.zcml
setup.cfg
setup.py
communesplone/__init__.py
communesplone.layout.egg-info/PKG-INFO
communesplone.layout.egg-info/SOURCES.txt
communesplone.layout.egg-info/dependency_links.txt
communesplone.layout.egg-info/entry_points.txt
communesplone.layout.egg-info/namespace_packages.txt
communesplone.layout.egg-info/not-zip-safe
communesplone.layout.egg-info/requires.txt
communesplone.layout.egg-info/top_level.txt
communesplone/layout/__init__.py
communesplone/layout/configure.zcml
communesplone/layout/mklocales.sh
communesplone/layout/profiles.zcml
communesplone/layout/setuphandlers.py
communesplone/layout/skins.zcml
communesplone/layout/svnignore
communesplone/layout/tests.py
communesplone/layout/version.txt
communesplone/layout/locales/README.txt
communesplone/layout/locales/communesplone.layout.pot
communesplone/layout/locales/plone.pot
communesplone/layout/locales/sync_pos.sh
communesplone/layout/locales/de/LC_MESSAGES/communesplone.layout.mo
communesplone/layout/locales/de/LC_MESSAGES/communesplone.layout.po
communesplone/layout/locales/de/LC_MESSAGES/plone.mo
communesplone/layout/locales/de/LC_MESSAGES/plone.po
communesplone/layout/locales/en/LC_MESSAGES/README.txt
communesplone/layout/locales/en/LC_MESSAGES/communesplone.layout.mo
communesplone/layout/locales/en/LC_MESSAGES/communesplone.layout.po
communesplone/layout/locales/en/LC_MESSAGES/plone.mo
communesplone/layout/locales/en/LC_MESSAGES/plone.po
communesplone/layout/locales/es/LC_MESSAGES/communesplone.layout.mo
communesplone/layout/locales/es/LC_MESSAGES/communesplone.layout.po
communesplone/layout/locales/es/LC_MESSAGES/plone.mo
communesplone/layout/locales/es/LC_MESSAGES/plone.po
communesplone/layout/locales/fr/LC_MESSAGES/README.txt
communesplone/layout/locales/fr/LC_MESSAGES/communesplone.layout.mo
communesplone/layout/locales/fr/LC_MESSAGES/communesplone.layout.po
communesplone/layout/locales/fr/LC_MESSAGES/plone.mo
communesplone/layout/locales/fr/LC_MESSAGES/plone.po
communesplone/layout/locales/nl/LC_MESSAGES/communesplone.layout.mo
communesplone/layout/locales/nl/LC_MESSAGES/communesplone.layout.po
communesplone/layout/locales/nl/LC_MESSAGES/plone.mo
communesplone/layout/locales/nl/LC_MESSAGES/plone.po
communesplone/layout/profiles/default/communesplone.layout_various.txt
