Metadata-Version: 1.1
Name: communesplone.layout
Version: 4.3.15.1
Summary: General layout adaptations
Home-page: http://svn.communesplone.org/svn/communesplone/communesplone.layout
Author: CommunesPlone.org
Author-email: support@communesplone.be
License: GPL
Platform: UNKNOWN
Classifier: Environment :: Web Environment
Classifier: Framework :: Plone
Classifier: Programming Language :: Python
